acquisition/__init__.py
acquisition/acquire.py
compute/__init__.py
compute/sink.py
compute/source.py
gateway/__init__.py
gateway/data_reader.py
gateway/data_store.py
lightspace-0.0.1.dist-info/METADATA
lightspace-0.0.1.dist-info/WHEEL
lightspace-0.0.1.dist-info/top_level.txt
lightspace-0.0.1.dist-info/RECORD
