Metadata-Version: 2.1
Name: lightspace
Version: 0.0.1
Summary: The lightspace package
Home-page: https://github.com/simulo
Author: Sanatan Sahgal
Author-email: sanatan@simulo.ai
Project-URL: Bug Tracker, https://github.com/simulo
Classifier: Programming Language :: Python :: 3
Classifier: License :: OSI Approved :: MIT License
Classifier: Operating System :: OS Independent
Requires-Python: >=3.6
